wenviro/__init__.py
wenviro/wenviro.py
wenviro-0.0.3.dist-info/METADATA
wenviro-0.0.3.dist-info/WHEEL
wenviro-0.0.3.dist-info/top_level.txt
wenviro-0.0.3.dist-info/RECORD
