Metadata-Version: 2.1
Name: wenviro
Version: 0.0.3
Summary: Envio variables helper
Home-page: https://github.com/gustavoghioldi/enviro
Author: Gustavo Ghioldi
Author-email: gustavoghioldir@gmail.com
License: UNKNOWN
Platform: UNKNOWN
Classifier: Programming Language :: Python :: 3
Classifier: License :: OSI Approved :: MIT License
Classifier: Operating System :: OS Independent
